blctools/__init__.py
blctools/cl_ApiCammesa.py
blctools/cl_ArchivoMDB.py
blctools/cl_BCRA.py
blctools/cl_CarpetaServicios.py
blctools/cl_DTE.py
blctools/cl_DatosCROM.py
blctools/cl_DatosCdO.py
blctools/cl_DatosSMEC.py
blctools/cl_PPO.py
blctools/cl_Pronosticos.py
blctools/cl_ReporteBase.py
blctools/cl_SQLConnector.py
blctools/cl_TablasVC.py
blctools/cl_UsuarioCammesa.py
blctools/dirs.py
blctools/eo.py
blctools/fechas.py
blctools/fv.py
blctools-0.0.46.dist-info/LICENSE
blctools-0.0.46.dist-info/METADATA
blctools-0.0.46.dist-info/WHEEL
blctools-0.0.46.dist-info/top_level.txt
blctools-0.0.46.dist-info/RECORD
