Metadata-Version: 2.1
Name: blctools
Version: 0.0.46
Summary: Tools to work with data inside BLCs MS Sharepoint Cloud & Database
Home-page: https://github.com/DiegoRioboCabot/blctools
Author: Diego Riobo Cabot
Author-email: riobocabotd@gmail.com
Project-URL: Bug Tracker, https://github.com/DiegoRioboCabot/blctools/issues
Classifier: Programming Language :: Python :: 3
Classifier: License :: OSI Approved :: MIT License
Classifier: Operating System :: OS Independent
Requires-Python: >=3.6
License-File: LICENSE
